awil_ft232h/__init__.py
awil_ft232h/awil_ft232h.py
awil_ft232h-0.1.4.dist-info/LICENSE
awil_ft232h-0.1.4.dist-info/METADATA
awil_ft232h-0.1.4.dist-info/WHEEL
awil_ft232h-0.1.4.dist-info/top_level.txt
awil_ft232h-0.1.4.dist-info/RECORD
