Metadata-Version: 2.1
Name: awil_ft232h
Version: 0.1.4
Author: Noriki Mochizuki
Author-email: noriki.mochizuki.mj@gmail.com
License: MIT
License-File: LICENSE
Requires-Dist: pyftdi >=0.55
